examples/BatchProcessing.py
examples/BufferExample.py
examples/ConditionBasedMaintenance.py
examples/DataExploration.py
examples/ExtendingPartObject.py
examples/FilterParts.py
examples/MachineFaultDetection.py
examples/MaintenanceOptimization.py
examples/OperatingSchedule.py
examples/PaperMillCmsEvaluation.py
examples/ParallelStations.py
examples/PartQuality.py
examples/ReentrantFlow.py
examples/SaveSimulationToFile.py
examples/SharedResources.py
examples/SharedResourcesComplex.py
examples/SimulateMultipleTimes.py
examples/SingleMachineWithFaults.py
examples/SingleProcessor.py
examples/VariousFlows.py
examples/__init__.py
examples/machine_with_damage.py
examples/machine_with_faults.py
simprocesd/__init__.py
simprocesd/model/__init__.py
simprocesd/model/resource_manager.py
simprocesd/model/simulation.py
simprocesd/model/system.py
simprocesd/model/cms/__init__.py
simprocesd/model/cms/cms.py
simprocesd/model/factory_floor/__init__.py
simprocesd/model/factory_floor/action_scheduler.py
simprocesd/model/factory_floor/asset.py
simprocesd/model/factory_floor/batch.py
simprocesd/model/factory_floor/buffer.py
simprocesd/model/factory_floor/decision_gate.py
simprocesd/model/factory_floor/group.py
simprocesd/model/factory_floor/maintainer.py
simprocesd/model/factory_floor/part.py
simprocesd/model/factory_floor/part_batcher.py
simprocesd/model/factory_floor/part_flow_controller.py
simprocesd/model/factory_floor/part_handler.py
simprocesd/model/factory_floor/part_processor.py
simprocesd/model/factory_floor/sink.py
simprocesd/model/factory_floor/source.py
simprocesd/model/sensors/__init__.py
simprocesd/model/sensors/part_sensor.py
simprocesd/model/sensors/sensor.py
simprocesd/utils/__init__.py
simprocesd/utils/math_utils.py
simprocesd/utils/simulation_info_utils.py
simprocesd/utils/utils.py
simprocesd-0.3.0.dist-info/LICENSE.md
simprocesd-0.3.0.dist-info/METADATA
simprocesd-0.3.0.dist-info/WHEEL
simprocesd-0.3.0.dist-info/top_level.txt
simprocesd-0.3.0.dist-info/RECORD
