Metadata-Version: 2.1
Name: simprocesd
Version: 0.3.0
Summary: Discrete event simulator for manufacturing systems.
Author: Serghei Drozdov
Author-email: serghei.drozdov@nist.gov
License: US Government Open Source
Project-URL: Source Code, https://github.com/usnistgov/simprocesd
Classifier: Development Status :: 3 - Alpha
Classifier: Programming Language :: Python
Classifier: Programming Language :: Python :: 3
Classifier: Programming Language :: Python :: 3.7
Classifier: Programming Language :: Python :: 3.9
Classifier: Programming Language :: Python :: 3.10
Classifier: Intended Audience :: Manufacturing
Classifier: Intended Audience :: Science/Research
Classifier: License :: OSI Approved :: MIT License
Classifier: Operating System :: OS Independent
Requires-Python: >=3.7
License-File: LICENSE.md
Requires-Dist: dill
Requires-Dist: matplotlib >=3.5
Requires-Dist: numpy >=1.21
Provides-Extra: examples
Requires-Dist: scipy >=1.7 ; extra == 'examples'
